{
    "Login": {
        "title": "Inicio",
        "loginClasic": "O sea clásico",
        "usernameEmail": "Nombre de usuario / Dirección de Email",
        "usernameRequired": "El nombre de usuario es obligatorio",
        "usernameMinimun": "Mínimo 3 caracteres",
        "usernameInvalid": "Nombre de usuario no válido",
        "usernamewrong": "Nombre de usuario o contraseña incorrectos",
        "password": "Contraseña",
        "passwordRequired": " La contraseña es obligatoria",
        "remember": "Recordar contraseña",
        "loginButton": "Conectarse",
        "resend": "Reenviar",
        "forgotPassword": "Olvidó la contraseña",
        "resendActivateMail": "Reenviar correo de activación",
        "error": "Error",
        "emailVerfied": "Correo electrónico verificado",
        "RecoveryPwd": {
            "title": "Reestablecer contraseña",
            "email":"Nombre de usuario / Dirección de email",
            "recover": "Recuperar",
            "backLogin": "Volver atrás para iniciar sesión",
            "changePwd": "Cambiar contraseña",
            "password": "Contraseña",
            "passwordRequired": " La contraseña es obligatoria",
            "passwordPattern": " Mínimo de 6 caracteres, 1 letra mayúscula, 1 letra miníscula, 1 número",
            "repeatPassword": "Repetir contraseña",
            "passwordMissmatch": "Las contraseñas no coinciden",
            "saveButton": "Guardar",
            "checkMail": "La recuperación de contraseña comenzó. Por favor compruebe sus emails.",
            "errorRecovery": "Error al recuperar la contraseña",
            "passwordUpdate": "Contraseña actualizada",
            "errorUpdate": "Error al actualizar"
        }
    },
    "Register": {
        "title": "Registro",
        "loginClasic": "O sea clásico",
        "userName": "Nombre de usuario...",
        "usernameRequired": "El nombre de usuario es obligatorio",
        "usernameMinimun": "Mínimo 3 caracteres",
        "firstName": "Nombre...",
        "firstNameRequired": "El nombre es obligatorio",
        "lasName": "Apellidos...",
        "lasNameRequired": "Los apellidos son obligatorios",
        "email": "Email...",
        "emailRequired": "El email es obligatorio",
        "emailMismatch": "Email mismatch",
        "emailIncalid": "Email no válido",
        "password": "Contraseña...",
        "passwordRequired": "La contraseña es obligatoria",
        "passwordPattern": "Mínimo de 6 caracteres, 1 letra mayúscula, 1 letra miníscula, 1 número",
        "passwprdRepeatInput": "Repetir contraseña...",
        "passwordRepeat": " Es obligatorio repetir la contraseña",
        "passwordMissmatch": "Las contraseñas no coinciden",
        "iAgree": "Estoy de acuerdo con",
        "termsConditions": "los Términos y Condiciones",
        "login": "Iniciar sesión",
        "getStart": "Empezar",
        "hackTools": "Uso de software malicioso detectado. Por favor rellene todos los campos y acepte los Términos y Condiciones de Servicio.",
        "checkEmail": "Compruebe su correo electrónico.",
        "error": "Error",
        "repeatEmail": "Repetir email..."
    },
    "Profile": {
        "MyProfile":{
            "title": "Mi perfil",
            "aboutMe": "Sobre mí:",
            "name": "Nombre:",
            "location": "Ubicación:",
            "memberSince": "Miembro desde:",
            "description": "Descripción",
            "readMore": "Leer más",
            "readLess": "Leer menos",
            "editProfileButton": "Editar perfil",
            "walletTitle": "Cartera",
            "wallet": "Cartera",
            "saveWalletButton": "Guardar Cartera",
            "walletNotifySave": "Cartera guardada.",
            "walletNotifyEmpty":"El campo está vacío.",
            "socialTitle": "Social",
            "editProfileTitle": "Editar perfil",
            "editProfileSubTitle": "Complete su perfil",
            "editProfileUsername": "Nombre de usuario",
            "editProfileUsernameMinimunCharacter": "The user name must contain a minimum of 3 characters, without spaces or special characters",
            "editProfileUsernamePattern": " El nombre de usuario puede contener solo A-Z, a-z, 0-9 y _",
            "editProfilePhone": "Teléfono móvil",
            "editProfilePhoneInvalid": "Número de teléfono no válido",
            "editProfileEmail": "Correo eléctrónico",
            "editProfileFirstname": "Nombre",
            "editProfileFirstnameRequired": "El nombre es obligatorio",
            "editProfileLastname": "Apellidos",
            "editProfileLastnameRequired": "Los apellidos son obligatorios",
            "editProfileCity": "Ciudad",
            "editProfileInvalidCity": "Nombre de ciudad no válido",
            "editProfileCountry": "País",
            "editProfileWebsite": "Página Web",
            "editProfileInvalidWebsite": "URL de la página Web no válida",
            "editProfileInvalidFacebook": "URL de Facebook no válida",
            "editProfileInvalidTwitter": "URL de Twitter no válida",
            "editProfileInvalidInstagram": "URL de Instagram no válida",
            "editProfileInvalidSoundcloud": "URL de SoundCloud no válida",
            "editProfileInvalidTwitch": "URL de Twitch no válida",
            "editProfileInvalidvVk": "URL de Vk no válida",
            "editProfileInvalidMusicoin": "URL de Musicoin no válida",
            "editProfileInvalidGoogle": "URL de Google plus no válida",
            "editProfileInvalidTumblr": "URL de Tumblr no válida",
            "editProfileInvalidPinterest": "URL de Pinterest no válida",
            "editProfileSomethingAboutYou": "Cuéntenos algo sobre usted...",
            "editProfileUpdateButton": "Actualizar perfil",
            "editProfileCancelButton": "Cancelar",
            "editProfileNotifySave": "Perfil actualizado",
            "editProfileNotifyError": "Error al actualizar",
            "editProfileChangePasswordTitle": "Cambiar contraseña",
            "editProfileOldPassword": "Contraseña anterior",
            "editProfileNewPassword": "Nueva contraseña",
            "editProfileNewPasswordPattern": "Mínimo de 6 caracteres, 1 letra mayúscula, 1 letra miníscula, 1 número",
            "editProfileRepeatNewPassword": "Repetir contraseña",
            "editProfileRepeatNewPasswordRequired": "Es necesario repetir la contraseña",
            "editProfileRepeatNewPasswordMissmatch": "Las contraseñas no coinciden",
            "editProfileUpdatePasswordButton": "Actualizar contraseña ",
            "editProfilePasswordNotifyError": "Error de actualización",
            "editProfilePasswordNotifyDifferent": "Error de actualización: las contraseñas son diferentes",
            "editProfilePasswordNotifyInsert": "Error de actualización: Introduzca las contraseñas",
            "editProfilePasswordNotifyPasswordEqual": "Error de actualización: La contraseña anterior y la nueva son iguales",
            "loginProfileTitle": "Es necesario iniciar sesión!",
            "loginProfileText": "Por favor inicie sesión para usar esta función",
            "loginProfileConfirmButton": "Ok",
            "loginProfileCancelButton": "Cancelar",
            "myProfile": "Mi Perfil",
            "playlist": "Playlists",
            "publications": "Publicaciones",
            "live": "Transmisiones en directo",
            "subscriptions": "Suscripciones",
            "security": "Seguridad",
            "language": "Mi idioma",
            "saveLanguage": "Guardar idioma",
            "languageSelect": "Idioma",
            "textEditorPlaceholder" : "Introduzca un texto...",
            "editProfilePasswordNotifySave": "Password saved successfully",
            "purchases": "My purchases",
            "singularProfilePurchase": "Purchase",
            "profilePurchase": "Purchases",
            "noPurchase": "There are no purchases",
            "subscribers": "Subscribers",
            "imageTooSmall":"The selected image is too small and could produce undesired results. For optimal result it is recommended that you chose a larger image.if you want to keep the selected image, click on (+) button to resize it.",
            "requiredFields": "Required fields"
        },
        "MyPurchases": {
            "channelStay": "Channel Stay",
            "channelStayText1": "Is the simplest way to promote your content by maintaining your visiting users within your channel.",
            "channelStayText2": "When you aquiere",
            "channelStayText3": "all related content shown to the visitor will be selected from your own channel.",
            "channelStayText4": "is a monthly service for your whole channel and costs 5 TUBES per month.",
            "channelStayButton": "Yes, I want Channel Stay",
            "channelStaySwalTitle": "Purchase channel stay",
            "channelStaySwalText1": "Yes, I want to keep the visiting users in my channel.",
            "channelStaySwalText2": "Purchase channel costs 5 TUBES",
            "channelStaySwalConfirmButton": "Yes, I want channel stay",
            "channelStaySwalCancelButton": "No, thank you",
            "perMonth": "Per month",
            "perUse": "Per use",
            "monthly": "Monthly",
            "monthlyCost": "Monthly costs 1000 Tube",
            "purchaseBuy": "Buy",
            "purchaseCancel": "Cancel",
            "Uses": "uses"
        },
        "MyPlaylists":{
            "title": "Mis playlists",
            "editPlaylistTitle": "Título",
            "editPlaylistDescription": "Descripción",
            "editPlaylistSaveButton": "Guardar",
            "editPlaylistDeleteButton": "Eliminar",
            "editPlaylistCloseButton": "Close playlist",
            "editPlaylistEmpty": "Esta playlist está vacía.",
            "newPlaylist": "Nueva playlist",
            "newPlaylistTitle": "Título",
            "newPlaylistDescription": "Descrición",
            "newPlaylistSaveButton": "Guardar",
            "deletePlaylistTitle": "¿Está seguro?",
            "deletePlaylistText": "Se eliminará la playlist para siempre",
            "deletePlaylistConfirmButton": "Sí, eliminar!",
            "deletePlaylistCancelButton": "Cancelar",
            "deletePlaylistTitleConfirm": "Eliminada!",
            "deletePlaylistTextConfirm": "Su playlist ha sido eliminada",
            "updatePlaylistTitle": "Actualizada!",
            "updatePlaylistText": "Los datos de su playlist han sido actualizados",
            "updatePlaylistName": "Error por favor introduzca el nombre",
            "deleteVideoPlaylistTitle": "¿Está seguro ?",
            "deleteVideoPlaylistText": "Se eliminará el video de la playlist",
            "deleteVideoPlaylistConfirmButton": "¡Sí, eliminar!",
            "deleteVideoPlaylistCancelButton": "Cancelar",
            "deleteVideoPlaylistTitleConfirm": "¡Eliminado!",
            "deleteVideoPlaylistTextConfirm": "Su archivo ha sido eliminado",
            "VideoPlaylistButton": "Ok",
            "noPlaylists": "No hay playlists"
        },
        "Publications":{
            "singularTitle": "Upload",
            "title": "Uploads",
            "views": "Visualizaciones",
            "edit": "Editar",
            "delete": "Eliminar",
            "deletePublicationTitle": "¿Está seguro?",
            "deletePublicationText": "Se eliminará la publicación",
            "deletePublicationConfirmButton": "¡Sí, eliminar publicación!",
            "deletePublicationCancelButton": "Cancelar",
            "deletePublicationNotify": "Su vídeo ha sido eliminado",
            "deletePublicationNotifyError": "Error",
            "videoInfoError": "Error al obtener info del vídeo",
            "noUploads": "No hay cargas",
            "editVideo": "Edit video",
            "makePrimaryVideo": "Set as primary video"
        },
        "LiveStreams": {
            "title": "Mis transmisiones en directo",
            "views": "Visualizaciones",
            "edit": "Editar",
            "noLiveStreams": "No hay transmisiones en directo"
        },
        "Subscriptions": {
            "singularTitle": "Subscription",
            "title": "Suscripciones",
            "subscriptionsButton": "Suscribirse",
            "unSubscriptionsButton": "Cancelar suscripción",
            "noSubscriptions": "No hay suscripciones"
        },
        "Subscribers": {
            "singularTitle": "Subscriber",
            "title": "Subscribers",
            "subscriptionsButton": "Subscribe",
            "unSubscriptionsButton": "Unsubscribe",
            "noSubscriptions": "There are no subscribers"
        },
        "Security": {
            "title": "Seguridad",
            "authentication": "Factor-2 de autenticación",
            "qr": "Escanear el código QR",
            "code": "Código",
            "twoFactorEnabled": "Habilitar",
            "twoFactorDisabled": "Deshabilitar",
            "nsfwEnabled": "NSFW habilitado",
            "nsfwDisabled" : "NSFW deshabilitado",
            "activateAuthenticationTitle": "AVISO",
            "activateAuthenticationText": "¡Asegúrese de que ha escaneado el código de autenticación en su app de autenticación, antes de continuar!",
            "activateAuthenticationConfirmButton": "Ok",
            "activateAuthenticationDeleteButton": "Cancelar",
            "nsfw": "Innapropiado para el trabajo (NSFW)",
            "enableNsfw": "¿ Seguro que quiere habilitar el contenido NSFW (Not Safe For Work) ?",
            "settings": "Settings",
            "membership": "Membership",
            "advertMessage": "It's very important that you save this recovery key in case you lose access to the Authenticator App:"
        }
    },
    "Dashboard": {
        "views": "Visualizaciones",
        "likes": "Likes",
        "addPlaylists": "Añadir a playlist",
        "newPlaylist": "Nueva playlist",
        "addPlaylistButton": "Añadir",
        "addPLaylistTitle":"Añadir a...",
        "live":"En directo",
        "ago": "ago",
        "recomended":"Recomendados",
        "newest": "Novedades",
        "trending": "Tendencias",
        "viewAll": "Ver más"
    },
    "Trending": {
        "views": "Visualizaciones",
        "likes": "Likes",
        "addPlaylists": "Añadir a playlist",
        "newPlaylist": "Nueva playlist",
        "addPlaylistButton": "Añadir",
        "addPLaylistTitle":"Añadir a...",
        "live":"En directo"
    },
    "Newcomers": {
        "views": "Visualizaciones",
        "likes": "Likes",
        "addPlaylists": "Añadir a playlist",
        "newPlaylist": "Nueva playlist",
        "addPlaylistButton": "Añadir",
        "addPLaylistTitle":"Añadir a...",
        "live":"En directo"
    },
    "Live": {
        "views": "Visualizaciones",
        "likes": "Likes",
        "noLivestreams": "Transmisiones en directo no disponibles",
        "live":"En directo"
    },
    "MediaEdit": {
        "title": "Editar medios",
        "snapshotButon": "Capturar imagen",
        "thumbnailButton": "Subir imagen",
        "videoTitle": "Título del vídeo",
        "videoTitleError": "El título necesita al menos 5 caracteres",
        "videoTag": "Por favor, añada alguna etiqueta",
        "videoPrivacy": "Privacidad",
        "videoCategory": "Categoría",
        "videoLanguage": "Idioma",
        "videoAgeVerification": "Verificación de edad",
        "videoUnpublishButton": "Eliminar publicación",
        "videoCancelButton": "Cancelar",
        "videoUpdateButton": "Actualizar",
        "videoPublishButton": "Publicar",
        "videoInputRequired": "Campo obligatorio",
        "videoUpdateDataNotify": "Sus datos se han actualizado con éxito..",
        "videoUpdateDataNotifyError": "Error de actualización",
        "videoUpdateDataRequired":"Por favor rellene los campos requeridos",
        "videoRemoved": "Su vídeo ha sido eliminado",
        "videoError": "Error",
        "videoRemovedConfirmTitle": "¿Está seguro?",
        "videoRemovedConfirmText": "Se eliminará la publicación",
        "videoRemovedConfirmButton": "Sí, eliminar publicación!",
        "videoRemovedConfirmCancel": "Cancelar",
        "videoPlaceholderEditor": "Introduzca aquí la descripción...",
        "uploadingImage": "Uploading image",
        "imageUploaded": "Image uploaded",
        "protectedContent": "Protected Content"
    },
    "Broadcast": {
        "Setings": {
            "title": "Ajustes",
            "Key": "Clave",
            "streamTitle": "Título de la emisión",
            "delete": "Eliminar",
            "edit": "Editar",
            "noKey": "Claves no encontradas",
            "generateNewKey": "Generar nueva clave",
            "yourStreamingUrl": "Su Url de la emisión",
            "yourStreamingKey": "Su clave de la emisión",
            "copyClipBoard": "Copiar la clave de la emisión al portapapeles",
            "cancel": "Cancelar",
            "save": "Guardar",
            "upload": "Cargar",
            "error": "Error",
            "ok": "Ok",
            "requiredFile": "Debe rellenar los campos requeridos",
            "requiredLoginTitle": "¡Es necesario iniciar sesión!",
            "requiredLoginText": "Por favor inicie sesión para usar esta función",
            "saved": "Sus datos se han guardado con éxito",
            "savedKey":"Su clave personal ha sido actualizada",
            "copiedClipBoard": "Su clave de emisión se ha copiado en el portapapeles",
            "copiedClipBoardTransmission": "Su URL de transmisión ha sido copiada al portapapeles",
            "confirmDeleteTitle": "Eliminar clave de emisión",
            "confirmDeleteText": "¿Está seguro que quiere eliminar esta clave de emisión?",
            "confirmDeleteButton": "ELIMINAR",
            "showhidden": "Show / Hide key "
        },
        "Tutorial": {
            "title": "Tutorial rápido",
            "1pTutorial": "Para configurar la emisión en directo haga clic en el botón \"Generar nueva clave\".",
            "2pTutorial": "Obtendrá su URL de emisión y su clave de emisión.",
            "3pTutorial": "O seleccione una de las claves existentes y haga clic en \"Editar\".",
            "4pTutorial": "Para configurar la vista en miniatura para su vídeo haga clic en el botón \"CARGAR\", seleccione un archivo multimedia y haga clic en abrir",
            "5pTutorial": "Rellene el campo del título de la emisión para nombrar su emisión. Use el editor de texto para escribir la descripción.",
            "6pTutorial": "Esto es todo lo que tiene que hacer para configurar su emisión, solo haga clic en GUARDAR.",
            "7pTutorial": "Comience la emisión en directo con el programa OBS.",
            "8pTutorial": "Abra el programa OBS, vaya a Configuración, seleccione la pestaña \"Emisión\", cambie el Tipo de Emisión a personalizar el servidor de retransmisión. Pegue la URL de su emisión en el campo URL, pegue la clave de su emisión en el campo de Clave de retransmisión. Aplique los ajustes. Haga clic en ACEPTAR para cerrar la ventana.",
            "9pTutorial": "Obtendrá la URL de la emisión y la clave de emisión desde la configuración de Bit.Tube, haga clic en el símbolo del clip para copiar ambos.",
            "10pTutorial": "Configure su emisión de OBS con escenas, fuentes y todas sus configuraciones preferidas y comience a emitir.",
            "11pTutorial": "Esto es todo lo que tiene que hacer para comenzar a emitir con OBS en Bit.Tube.",
            "titleStream,": "Software de transmisión",
            "1pTutorialStream": "Puede transmitir sus contenidos en la plataforma de Bit.Tube usando una aplicación de software especial. El contenido está asociado a una dirección de cartera de BitTube que identifica al titular de los derechos de autor. ¡Hemos hecho algunas sugerencias a continuación, elija una de ellas y comience!",
            "2pTutorialStream": "Open Broadcaster Software",
            "3pTutorialStream": "Open Broadcaster Software, o mejor conocido como OBS es un software de código abierto programado en C y C++ para la grabación y transmisión de vídeo en directo. OBS permite una captura en tiempo real y el usuario tiene control total sobre la composición de la escena, la codificación, la grabación y la transmisión. Mientras tanto, OBS se presenta con una variedad de plug-ins, que ofrecen al usuario mucha libertad para configurar, planificar y realizar su transmisión.",
            "4pTutorialStream": "Gameshow",
            "5pTutorialStream": "Un software de pago para la retransmisión de juegos que combina en uno efectividad y facilidad de uso. ",
            "6pTutorialStream": "Tanto si elige configurar su transmisión desde una plantilla determinada o como si hace sus propias configuraciones usando las funciones del software, su transmisión será siempre perfecta, con una aperiencia profesional. Perfecto para profesionales y novatos al mismo tiempo.",
            "7pTutorialStream": "XSplit Gamecaster",
            "8pTutorialStream": "La forma más sencilla de comenzar a transmitir o grabar su PC o consola de juegos, tal y como se dice. Use XSplit Gamecaster para compartir su partida. Tan solo haga clic para emitir y grabar sus momentos especiales de juego. También puede elegir XSplit Broadcaster, como alternativa para la transmisión.",
            "9pTutorialStream": "Vmix",
            "10pTutorialStream": " Ampliamente utilizado, vMix es la herramienta ideal para la transmisión, especialmente para vloggers, pero no solo eso. vMix es una solución completa de software de producción de vídeo en vivo con funciones que incluyen mezcla en directo, conmutación, grabación y transmisión en directo de fuentes de vídeo 4K, SD o HD incluyendo cámaras, archivos de vídeo, DVDs, imágenes, Powerpoint y mucho mucho más.",
            "dowloadButton": "Descargar"
        },
        "CreateKey":{
                "noWallet": "You don't have a wallet",
                "noWalletText": "In this way, you will not receive any revenue for this broadcast",
                "cancelWalletButton" : "Cancel",
                "createWalletButton": "Create Wallet"
        }
    },
    "Play": {
        "addPlaylists": "Añadir a la playlist",
        "newPlaylist": "Nueva playlist",
        "addPlaylistButton": "Añadir",
        "addPLaylistTitle":"Añadir a...",
        "views": "visualizaciones",
        "viewers": "espectadores",
        "donate": "Donar",
        "likes": "Likes",
        "writeComment": "Escribir un comentario",
        "addPlaylist": "Añadir a la playlist",
        "embedCode": "Obtener código embed",
        "reportVideo": "Denunciar vídeo",
        "share": "Compartir",
        "editVideo": "Editar vídeo",
        "subscribe": "Suscribirse",
        "unSubscribe": "Cancelar suscripción",
        "showMore": "Mostrar más",
        "showLess": "Mostrar menos",
        "commentButton": "Comentar",
        "cancel": "Cancelar",
        "singularComments": "comment",
        "comments": "Comentarios",
        "madePost": "hizo un post.",
        "justNow": "Ahora mismo",
        "madeSubPost": "hizo un subpost.",
        "replyComment": "Respuesta al comentario",
        "commentEdit": "Editar comentario",
        "edit": "Editar",
        "autoPlay": "Autoplay",
        "next": "Siguiente",
        "related": "Relacionado",
        "live": "En directo",
        "playlist": "Playlist",
        "loadMore": "Cargar más",
        "seeAnswer": "See reply",
        "seeAnswers": "See replies",
        "hideAnswer": "Hide reply",
        "hideAnswers": "Hide replies",
        "copyClipboardIframe": "Iframe copiado al portapapeles",
        "copyClipboard": "Copiar al portapapeles",
        "embedVideoTitle": "Video incrustado",
        "loginProfileTitle": "Es necesario iniciar sesión!",
        "loginProfileText": "Por favor inicie sesión para usar esta función",
        "loginProfileConfirmButton": "Ok",
        "loginProfileCancelButton": "Cancelar",
        "deleteComentConfirmTitle": "Eliminar comentario",
        "deleteComentConfirmText": "¿Está seguro que quiere eliminar este comentario?",
        "deleteComentConfirmButton": "Sí",
        "reportVideoInnapropiateContent": "Contenido inapropiado",
        "reportVideoCopyrightViolation": "Violación del Copyright",
        "reportVideoOther": "Otro",
        "reportVideoCancel": "Cancelar",
        "reportVideoSend": "Enviar",
        "textEditorPlaceholder": "Introducir un texto...",
        "AcceptedHashesText": "Hashes aceptados: ",
        "HashesText": "Hash/s: ",
        "TotalHashesText": "Airtime PoV: ",
        "status": "Estado: ",
        "localSaving": "Ahorros de IPFS local: ",
        "RTCPeers": "RTC Peers: ",
        "saving": "RTC Ahorros: ",
        "wallet": "Cartera: ",
        "CloseStats": "Cerrar",
        "consent": "Al visualizar este contenido está ayudando a su creador.",
        "consent2": "Mientras visualiza contenidos, una parte no utilizada de la potencia de cálculo de su ordenador será usada para la cryptominería en favor del creador de dichos contenidos.",
        "agree": "Estoy de acuerdo",
        "innapropiateVideo": "Este vídeo puede ser inapropiado para algunos usuarios. Por favor confirme para continuar.",
        "working": "Trabajando",
        "waiting": "Esperando",
        "tipChannel": "Tip channel",
        "amount": "Amount",
        "2faCode": "2FA Code",
        "tip": "Tip",
        "close": "Close",
        "mediaReport": "Media report",
        "primaryVideo": "Set as primary video",
        "abortError": "User aborted media playback",
        "networkError": "There is a problem with your internet connection",
        "decodeError": "This media appears to be corrupted",
        "srcError": "This media appears to be corrupted",
        "encryptedError": "This content is premium, please purchase",
        "offlineStream": "Your desired stream appears to be offline",
        "popOutVideo": "Popout video",
        "cinemaMode": "Cinema mode",
        "setPrimaryVideo": "Saved primary video",
        "errorSavePrimaryVideo": "Error",
        "copyrightReport": "Report Copyright Violation",
        "yesUnpublish": "Yes unpublish",
        "copyrigthTextSwal": "This video will be flagged and unpublished to undergo further review. Are you sure you want to continue?",
        "iAmTheCopyright": "Yes, I am the copyright owner",
        "iAmRepresentCopyright":"Yes, I represent the copyright owner",
        "liveUnpublished": "Livestream unpublished",
        "liveUnpublishedError": "Livestream unpublish error",
        "reply": "Reply",
        "delete": "Delete",
        "writeReply": "Write a reply",
        "reportThisVideo": "Reportar este video",
        "ok": "ok",
        "errorHash": "No se puede encontrar el video seleccionado",
        "totalAirtimeText": "PoV:"
    },
    "Wallet": {
        "title": "Información general",
        "walletAdress": "Dirección de Cartera",
        "balance": "Balance",
        "offlineWallet": "Cartera Offline",
        "walletMaintenance": "cartera bajo mantenimiento",
        "walletBackSoon": "La cartera estará disponible en breve",
        "transactions": "Transacciones",
        "status": "Estado",
        "date": "Fecha",
        "amount": "Importe",
        "address": "Dirección",
        "paymentID": "ID de pago",
        "contacts": "Contactos",
        "name": "Nombre",
        "adress": "Dirección",
        "close": "Cerrar",
        "remoceContact": "Eliminar contacto",
        "addContact": "Añadir contacto",
        "sendtoAddress" : "Enviar a la dirección",
        "receiverAddress" : "Dirección del receptor",
        "ipbcAmount" : "Importe Tube",
        "feeIPBC" : "Cuota (Tube)",
        "anonymityLevel" : "Nivel de anonimato",
        "2FACode": "Código 2FA",
        "send": "Enviar",
        "cancel": "Cancelar",
        "walletKeys": "Claves de la cartera",
        "spendKey": "Clave para gastar",
        "viewKey": "Ver clave",
        "privatekey" : "Clave Privada",
        "errorRemoveContact": "¡Por favor seleccione un contacto para eliminar!",
        "removeContact": "Contacto eliminado...",
        "failedRemoveContact": "Fallo al eliminar el contacto...",
        "failedRetriveContact": "Fallo al recuperar contactos...",
        "2FAInvalid": "código 2FA no válido...",
        "fee": "La cuota no debe ser inferior a 0.01 IPBC",
        "Anonymity": "El anonimato debe estar entre 0 - 10",
        "transactionFaild": "Transacción fallida...",
        "noTransactions": "No hay transacciones",
        "unlocked": "Unlocked",
        "locked" : "Locked",
        "saveContact": "Save Contact",
        "closeContact": "Close",
        "sedWallet": "Send",
        "contactsWallet": "Contacts",
        "keyWallet": "Key",
        "noContactsfound": "No contacts found",
        "keyHasbeencopied": "Your key has been copied to the clipboard",
        "copyWalletClipboard": "Copy wallet to clipboard",
        "addnewContact": "Add New Contact",
        "mustContactName": "You must enter a contact name!",
        "invalidIPB": "Invalid BitTube Address!",
        "contactAdded": "Contact Added...",
        "contactAddedFail": "Failed to add contact...",
        "notEnoughBalance": "Not enough wallet balance or still locked.",
        "walletMaintenaceTitle": "Online wallet under maintenance",
        "walletMaintenaceText": "The online wallet is undergoing maintenace, please try again later",
        "walletDowload": "Download offline wallet",
        "walletCancel": "Ok",
        "copySpendKey": "Copy spend key to clipboard",
        "copyViewKey": "Copy view key to clipboard"
    },
    "Profitcalc": {
        "openCoinmarketcapButton": "Abrir Coinmarketcap",
        "exchanges": "Plataformas de intercambios",
        "livecoin": "Livecoin",
        "last": "Último",
        "high": "Más Alto",
        "low": "Más Bajo",
        "OpenLivecoin": "Abrir Livecoin",
        "tradeOgre": "TradeOgre",
        "tradeOgreOpen": "Abrir TradeOgre",
        "openCrex24": "Abrir Crex24",
        "altex": "Altex",
        "noAPI" : "No API",
        "crex24": "Crex24",
        "tpl_title" : "Calculadora de beneficios",
        "tpl_market" : "Mercado",
        "tpl_avg_hashrate" : "Promedio de Hashrate (H/s)",
        "tpl_avg_watchtime" : "Promedio de tiempo de reproducción (en horas)",
        "tpl_dayly_views" : "Visualizaciones diarias",
        "tpl_profit" : "Beneficios",
        "tpl_per_day" : "por día",
        "tpl_per_week" : "por semana",
        "tpl_per_month" : "por mes",
        "tpl_per_year" : "por año",
        "tpl_loading" : "Cargando...",
        "tpl_marketcap" : "CAPITALIZACIÓN DE MERCADO",
        "tpl_vol_usd_24h" : "VOLUMEN USD (24H)",
        "tpl_vol_eur_24h" : "VOLUMEN EUR (24H)"
    },
    "Upload": {
        "titleUpload": "Cargar archivos multimedia",
        "p1Upload": "Puede cargar sus archivos multimedia. Los archivos de vídeo resultantes estarán disponibles en múltiples formatos de calidad.",
        "p2Upload": "Nota: Calidad mínima 360P, duración menos de 3 horas y tamaño menor de 5 GB",
        "uploadNowButton": "Cargar ahora",
        "titleUploadYoutube": "Conectar a Youtube",
        "p1UploadYoutube": "Aquí puede conectarse directamente con su cuenta de Youtube y migrar con solo un clic su canal de Youtube a Bit.Tube",
        "conectYoutubeButton": "Conectar ahora",
        "snapshotButon": "Capturar imagen",
        "thumbnailButton": "Subir imagen",
        "videoTitle": "Título del vídeo",
        "videoTitleError": "El título necesita al menos 5 caracteres",
        "videoTag": "Por favor añada alguna etiqueta",
        "videoTagEnter": "Presione Enter después de cada etiqueta",
        "videoPrivacy": "Privacidad",
        "videoCategory": "Categoría",
        "videoLanguage": "Idioma",
        "videoAgeVerification": "Verificación de edad",
        "videoUnpublishButton": "Eliminar publicación",
        "videoUploadButton": "Cargar",
        "videoDiscardButton": "Descartar",
        "videoPublishButton": "Publicar",
        "videoInputRequired": "Campo obligatorio",
        "videoPlaceholderEditor": "Introducir descripción aquí...",
        "uploadMaintenance": "Lo sentimos, nuestro servicio para realizar cargas está en modo de mantenimiento, por favor inténtelo más tarde.",
        "uploadMaintenanceButton": "¡Entendido!",
        "uploadNetworkFail": "There is a problem with your internet connection. Please check.",
        "uploadWaiting": "WAITING UPLOAD SLOT",
        "noWallet": "Usted no tiene una cartera",
        "noWalletText": "De esta forma, no recibirá ningún ingreso por este vídeo.",
        "cancelWalletButton" : "Cancel",
        "createWalletButton": "Crear Cartera",
        "loginProfileTitle": "¡Es necesario iniciar sesión!",
        "loginProfileText": "Por favor inicie sesión para usar está función",
        "loginProfileConfirmButton": "Ok",
        "loginProfileCancelButton": "Cancelar",
        "videoAlreadyPublishedTitle": "¡Vídeo ya publicado!",
        "videoAlreadyPublishedText": "Puede editar este vídeo en su perfil bajo el apartado publicaciones",
        "videoSuccessfuly": "Your video has been successfully uploaded, you will receive a notification once your video has been published.",
        "authorizationYoutube": "En caso de no recibir autorización, por favor haga clic en AUTORIZAR y siga los pasos para dar autorización para comprobar su contenido de Youtube.",
        "authorizeButton": "Autorizar",
        "UnauthorizeButton": "No autorizar",
        "yourVideo":"Sus vídeos de Youtube",
        "selectAll": "Seleccionar todo",
        "startImport": "Iniciar importación",
        "videos": "Vídeos",
        "dataProteccion": "Protección de datos",
        "moreVideos": "Más vídeos",
        "allVideosAlready": "Todos los vídeos en este canal han sido ya cargados",
        "leavePageTitle": "¿Esta seguro que quiere abandonar esta página?",
        "leavePageText": "Se perderán todas sus cargas pendientes",
        "leavePageButton": "¡Sí, salir!",
        "needsRemove": "La autorización de Youtube debe ser eliminada.",
        "finalizeProcess": "Para finalizar este proceso, por favor visite la página de administración de cuentas de Google para eliminar por completo el acceso de",
        "bitubeIntegrate": "Integración de BitTube con YouTube",
        "areYouSure": "¿Está seguro?",
        "removeAccess": "¡Esto eliminará su acceso a su cuenta de Youtube!",
        "proceed": "¡Sí, proceder!",
        "gotit": "¡Entendido!",
        "allYourSelected": "Todos sus vídeos se han cargado con éxito, puede llevar un tiempo mientras se comprueban y se publican",
        "textEditorPlaceholder": "Introduzca un texto aquí...",
        "invalidFile": "INVALID FILE ERROR",
        "informationError": "INFORMATION ERROR",
        "transcodingError": "TRANSCODING ERROR",
        "syncError": "SYNCHRONIZATION ERROR",
        "pinError": "PIN ERROR",
        "sshError": "SSH ERROR",
        "qualityError": "The video quality is too low, it need to be at least 360p",
        "processing": "PROCESSING ",
        "waitingSync": "WAITING FOR SYNC",
        "syncing": "SYNCING ",
        "waitingPinning": "WAITING FOR PINNING",
        "pinning": "PINNING ",
        "done": "DONE",
        "uploading": "UPLOADING ",
        "initializing": "INITIALIZING",
        "waitingQueue": "WAITING IN QUEUE ",
        "downloading": "DOWNLOADING",
        "waitingTranscode": "WAITING FOR TRANSCODE",
        "internalError": "An internal error has occurred, please try again later",
        "areYouSureLose": "Are you sure? You will loose all your unsaved jobs!",
        "job": "Job",
        "priceInTube": "Price in TUBE",
        "priceInUsd": "Price in USD",
        "rental": "Rental",
        "purchase": "Purchase",
        "lifetime": "Lifetime",
        "rental24hrs": "24 hrs",
        "rental48hrs": "48 hrs",
        "rental72hrs": "72 hrs",
        "awaitTranscode":"VIDEO ACCEPTED, WAITING FOR PROCESSING",
        "regularUploadMaintenanceText": "We are sorry, but the Upload service is temporarily undergoing maintenance.",
        "regularUploadMaintenancetitle": "Upload under maintenance",
        "youtubeUploadMaintenanceText": "We are sorry, but the Youtube importer service is temporarily undergoing maintenance.",
        "youtubeUploadMaintenancetitle": "YouTube importer under maintenance",
        "premiumContent": "Premium content",
        "notPreviewed": "This video type can not be previewed.",
        "selectThumbnail" : "Please, select a thumbnail before uploading.",
        "videoSubcategory": "Subcategory"
    },
    "User": {
        "subscribe": "Suscribir",
        "unSubscribe": "Cancelar suscripción",
        "myProfile": "Mi perfil",
        "playlist": "Playlists",
        "publications": "Publicaciones",
        "live": "Transmisiones en directo",
        "subscriptions": "Suscripciones",
        "loginProfileTitle": "¡Es necesario iniciar sesión!",
        "loginProfileText": "Por favor inicie sesión para usar esta función",
        "loginProfileConfirmButton": "Ok",
        "loginProfileCancelButton": "Cancelar",
        "Profile": {
            "title": "Información general",
            "about": "Sobre",
            "name": "Nombre",
            "member": "Miembro desde",
            "description": "Descripción",
            "location": "Ubicación",
            "readMore": "Leer más",
            "readLess": "Leer menos",
            "social": "Social",
            "newest": "newest",
            "popular": "popular",
            "oldest": "oldest"
        },
        "Publications": {
           "publication": "Publicación",
            "publications": "Publicaciones",
            "noPublications": "No hay publicaciones",
            "live": "En directo",
            "addPlaylists": "Añadir a playlist",
            "newPlaylist": "Nueva playlist",
            "addPlaylistButton": "Añadir",
            "addPLaylistTitle":"Añadir a...",
            "ReadMore": "Read more",
            "showAll": "Show all",
            "sortedBy": "Sorted by",
            "sortBy": "Sort By",
            "sortByOldest": "Oldest",
            "sortByRecent": "Most recent",
            "sortByPopularity": "Popularity",
            "sortByRelevance" : "Relevance"
        },
        "LiveTv": {
            "livestream": "Transmisión en directo",
            "livestreams": "Transmisiones en directo",
            "noStream": "No hay transmisiones en directo",
            "live": "En directo",
            "addPlaylists": "Añadir a playlist",
            "newPlaylist": "Nueva playlist",
            "addPlaylistButton": "Añadir",
            "addPLaylistTitle":"Añadir a..."
        },
        "Subscriptions": {
            "subscriptions": "Suscripciones",
            "subscription": "Suscripcion",
            "nosubscriptions": "No hay suscripciones",
            "subscribe": "Suscribirse",
            "unSubscribe": "Cancelar suscripción"
        },
        "MyPlaylists": {
            "myPlaylists": "Mis Playlists",
            "noPlaylists": "No hay playlists",
            "description": "Descripción",
            "noDescription": "Sin descripción",
            "addMyPlaylist": "Añadir a mis Playlists",
            "addPlaylists": "Añadir a playlist",
            "newPlaylist": "Nueva playlist",
            "addPlaylistButton": "Añadir",
            "addPLaylistTitle":"Añadir a...",
            "playlistEmpty": "Esta playlist está vacía",
            "yourCopyPlaylist": "¡Usted tiene su propia copia de esta playlist!",
            "somenthingWrong": "¡Algo salió mal durante el proceso!"
        }
    },
    "LiveChat": {
        "title": "Chat en directo",
        "saySomething": "Decir algo",
        "chatUser": "Usuarios del Chat",
        "block": "Bloquear",
        "unblock": "Desbloquear",
        "blockFromChannel": "Bloquear desde el canal",
        "UnBlockFromChannel": "Desbloquear desde el canal",
        "loginProfileTitle": "Es necesario iniciar sesión!",
        "loginProfileText": "Por favor inicie sesión para usar esta función",
        "loginProfileConfirmButton": "Ok",
        "loginProfileCancelButton": "Cancelar"
    },
    "Playlist": {
        "loginProfileTitle": "¡Es necesario iniciar sesión!",
        "loginProfileText": "Por favor inicie sesión para usar esta función",
        "loginProfileConfirmButton": "Ok",
        "loginProfileCancelButton": "Cancelar"
    },
    "Result": {
        "noResult": "No se encontraron resultados",
        "live": "En directo",
        "addMyPlaylist": "Añadir a mis Playlists",
        "addPlaylists": "Añadir a playlist",
        "newPlaylist": "Nueva playlist",
        "addPlaylistButton": "Añadir",
        "addPLaylistTitle":"Añadir a...",
        "subscribe": "Suscribirse",
        "unSubscribe": "Cancelar suscripción",
        "goProfile": "Ir a mi perfil",
        "loginProfileTitle": "Es necesario iniciar sesión!",
        "loginProfileText": "Por favor inicie sesión para usar esta función",
        "loginProfileConfirmButton": "Ok",
        "loginProfileCancelButton": "Cancelar",
        "playlistCloned": "Playlist had been added to your playlists",
        "playlistClonedFailed": "You already cloned this playlist",
        "subscribers": "subscribers"
    },
    "Lenguages":{
        "languages_array":[  
            {"value": "AF", "viewValue": "Africaans"},
            {"value": "SQ", "viewValue": "Albanés"},
            {"value": "AR", "viewValue": "Árabe"},
            {"value": "HY", "viewValue": "Armenio"},
            {"value": "AZ", "viewValue": "Azerbaijan"},
            {"value": "EU", "viewValue": "Vasco"},
            {"value": "BN", "viewValue": "Bengalí"},
            {"value": "BG", "viewValue": "Búlgaro"},
            {"value": "CA", "viewValue": "Catalan"},
            {"value": "KM", "viewValue": "Camboyano"},
            {"value": "ZH", "viewValue": "Chino (Mandarin)"},
            {"value": "HR", "viewValue": "Croata"},
            {"value": "CS", "viewValue": "Checo"},
            {"value": "DA", "viewValue": "Danés"},
            {"value": "NL", "viewValue": "Holandés"},
            {"value": "EN", "viewValue": "Inglés"},
            {"value": "ET", "viewValue": "Estonio"},
            {"value": "FJ", "viewValue": "Fiyi"},
            {"value": "FI", "viewValue": "Finlandés"},
            {"value": "FR", "viewValue": "Francés"},
            {"value": "KA", "viewValue": "Georgiano"},
            {"value": "DE", "viewValue": "Alemán"},
            {"value": "EL", "viewValue": "Griego"},
            {"value": "GU", "viewValue": "Gujarati"},
            {"value": "HE", "viewValue": "Hebreo"},
            {"value": "HI", "viewValue": "Hindi"},
            {"value": "HU", "viewValue": "Húngaro"},
            {"value": "IS", "viewValue": "Islandés"},
            {"value": "ID", "viewValue": "Indonesio"},
            {"value": "GA", "viewValue": "Irlandés"},
            {"value": "IT", "viewValue": "Italiano"},
            {"value": "JA", "viewValue": "Japonés"},
            {"value": "JW", "viewValue": "Javanés"},
            {"value": "KO", "viewValue": "Coreano"},
            {"value": "LA", "viewValue": "Latin"},
            {"value": "LV", "viewValue": "Letón"},
            {"value": "LT", "viewValue": "Lituano"},
            {"value": "MK", "viewValue": "Macedonio"},
            {"value": "MS", "viewValue": "Malayo"},
            {"value": "ML", "viewValue": "Malayalam"},
            {"value": "MT", "viewValue": "Maltés"},
            {"value": "MI", "viewValue": "Maorí"},
            {"value": "MR", "viewValue": "Marathi"},
            {"value": "MN", "viewValue": "Mongol"},
            {"value": "NE", "viewValue": "Nepali"},
            {"value": "NO", "viewValue": "Noruego"},
            {"value": "FA", "viewValue": "Persa"},
            {"value": "PL", "viewValue": "Polaco"},
            {"value": "PT", "viewValue": "Portugués"},
            {"value": "PA", "viewValue": "Punjabi"},
            {"value": "QU", "viewValue": "Quechua"},
            {"value": "RO", "viewValue": "Rumano"},
            {"value": "RU", "viewValue": "Ruso"},
            {"value": "SM", "viewValue": "Samoano"},
            {"value": "SR", "viewValue": "Serbio"},
            {"value": "SK", "viewValue": "Eslovaco"},
            {"value": "SL", "viewValue": "Esloveno"},
            {"value": "ES", "viewValue": "Español"},
            {"value": "SW", "viewValue": "Swahili"},
            {"value": "SV", "viewValue": "Sueco "},
            {"value": "TA", "viewValue": "Tamil"},
            {"value": "TT", "viewValue": "Tártaro"},
            {"value": "TE", "viewValue": "Telugu"},
            {"value": "TH", "viewValue": "Tailandés"},
            {"value": "BO", "viewValue": "Tibetano"},
            {"value": "TO", "viewValue": "Tonga"},
            {"value": "TR", "viewValue": "Turco"},
            {"value": "UK", "viewValue": "Ucraniano"},
            {"value": "UR", "viewValue": "Urdu"},
            {"value": "UZ", "viewValue": "Uzbeko"},
            {"value": "VI", "viewValue": "Vietnamita"},
            {"value": "CY", "viewValue": "Galés"},
            {"value": "XH", "viewValue": "Xhosa"}
        ]
    },
    "DataProteccion" : {
        "data_protection_array":[
            {"value": "1", "viewValue": "Todos"},
            {"value": "2", "viewValue": "Soloyo (Próximamente)"},
            {"value": "3", "viewValue": "OnlyIFollow (Próximamente)"},
            {"value": "4", "viewValue": "Contraseña (Próximamente)"},
            {"value": "5", "viewValue": "Yoelijo (Próximamente)"},
            {"value": "6", "viewValue": "NotList (Próximamente)"},
            {"value": "7", "viewValue": "Linkprivado (Próximamente)"}
        ]
    },
    "Category": {
        "category_array":[
            {"value": "45", "viewValue": "Adulto (no porno)"},
            {"value": "24", "viewValue": "Arte y Cultura"},
            {"value": "26", "viewValue": "Moda y Belleza"},
            {"value": "37", "viewValue": "Coches"},
            {"value": "8", "viewValue":  "Cine"},
            {"value": "16", "viewValue": "Coaching"},
            {"value": "42", "viewValue": "Comedia"},
            {"value": "41", "viewValue": "Crypto"},
            {"value": "12", "viewValue": "Economía"},
            {"value": "3", "viewValue":  "E-Learning"},
            {"value": "22", "viewValue": "Entretenimiento"},
            {"value": "35", "viewValue": "Finanzas"},
            {"value": "36", "viewValue": "Comida"},
            {"value": "18", "viewValue": "Gadgets y Apps"},
            {"value": "2", "viewValue":  "Gaming"},
            {"value": "19", "viewValue": "Salud"},
            {"value": "15", "viewValue": "Historia"},
            {"value": "27", "viewValue": "Hobbies y Manualidades"},
            {"value": "23", "viewValue": "Niños"},
            {"value": "25", "viewValue": "Lifestyle"},
            {"value": "33", "viewValue": "Películas"},
            {"value": "5", "viewValue":  "Musica"},
            {"value": "20", "viewValue": "Naturaleza"},
            {"value": "9", "viewValue":  "Noticias"},
            {"value": "29", "viewValue": "Otros"},
            {"value": "44", "viewValue": "Artes escénicas"},
            {"value": "40", "viewValue": "Mascotas"},
            {"value": "28", "viewValue": "Religion"},
            {"value": "17", "viewValue": "PC Software/Hardware"},
            {"value": "39", "viewValue": "Porno"},
            {"value": "14", "viewValue": "Ciencia"},
            {"value": "31", "viewValue": "Series"},
            {"value": "13", "viewValue": "Temas Sociales"},
            {"value": "11", "viewValue": "Sociedad"},
            {"value": "6", "viewValue":  "Deportes"},
            {"value": "38", "viewValue": "Técnica"},
            {"value": "32", "viewValue": "Trailer"},
            {"value": "21", "viewValue": "Viajar"},
            {"value": "4", "viewValue":  "Cadenas TV"},
            {"value": "7", "viewValue":  "Vloggers"},
            {"value": "30", "viewValue": "Camera"},
            {"value": "34", "viewValue": "Yousician"}
        ],
        "category_array_xxx": [
            { "value": "3901", "viewValue": "Arab" },
            { "value": "3902", "viewValue": "Amateur" },
            { "value": "3903", "viewValue": "Asian" },
            { "value": "3904", "viewValue": "Anal" },
            { "value": "3905", "viewValue": "Babe" },
            { "value": "3906", "viewValue": "Big tits" },
            { "value": "3907", "viewValue": "Blowjob" },
            { "value": "3908", "viewValue": "Brunette" },
            { "value": "3909", "viewValue": "Bukkake" },
            { "value": "3910", "viewValue": "Big ass" },
            { "value": "3911", "viewValue": "Bondage" },
            { "value": "3912", "viewValue": "Cartoon" },
            { "value": "3913", "viewValue": "Casting" },
            { "value": "3914", "viewValue": "Creampie" },
            { "value": "3915", "viewValue": "Compilation" },
            { "value": "3916", "viewValue": "Cumshot" },
            { "value": "3917", "viewValue": "College" },
            { "value": "3918", "viewValue": "Double penetration" },
            { "value": "3919", "viewValue": "Fetish" },
            { "value": "3920", "viewValue": "Fisting" },
            { "value": "3921", "viewValue": "Gangbang" },
            { "value": "3922", "viewValue": "Gay" },
            { "value": "3923", "viewValue": "Handjob" },
            { "value": "3924", "viewValue": "Interracial" },
            { "value": "3925", "viewValue": "Lesbian" },
            { "value": "3926", "viewValue": "Latina" },
            { "value": "3927", "viewValue": "MILF" },
            { "value": "3928", "viewValue": "Massage" },
            { "value": "3929", "viewValue": "Masturbation" },
            { "value": "3930", "viewValue": "Mature" },
            { "value": "3931", "viewValue": "Old/Young" },
            { "value": "3932", "viewValue": "Orgy" },
            { "value": "3949", "viewValue": "Others" },
            { "value": "3933", "viewValue": "Pissing" },
            { "value": "3934", "viewValue": "Parody" },
            { "value": "3935", "viewValue": "Party" },
            { "value": "3936", "viewValue": "POV" },
            { "value": "3937", "viewValue": "Pornstar" },
            { "value": "3938", "viewValue": "Public" },
            { "value": "3939", "viewValue": "Role play" },
            { "value": "3940", "viewValue": "Rough sex" },
            { "value": "3941", "viewValue": "Romantic" },
            { "value": "3942", "viewValue": "Squirt" },
            { "value": "3943", "viewValue": "School" },
            { "value": "3944", "viewValue": "Sexy girls" },
            { "value": "3945", "viewValue": "Soft porn" },
            { "value": "3946", "viewValue": "Teen" },
            { "value": "3947", "viewValue": "Threesome" },
            { "value": "3948", "viewValue": "Toys" },
            { "value": "3950", "viewValue": "Virtual Reality" }
        ],
        "category_array_adult": [
            { "value": "4501", "viewValue": "Blood Content" },
            { "value": "4504", "viewValue": "NSFW" },
            { "value": "4503", "viewValue": "Others" },
            { "value": "4502", "viewValue": "Violent Content" }
        ]
    },
    "FixedPlugin": {
        "filters": "Filtros barra lateral",
        "background": "Fondo barra lateral",
        "mini": "Barra lateral mini",
        "image": "Imagen de la barra lateral",
        "night": "Modo noche",
        "selectImage": "Imágenes"
    },
	"Sidebar": {
        "homeSection": "Inicio",
        "trendingSection": "Tendencias",
        "newcomersSection": "Novedades",
        "liveSection": "En Directo",
        "uploadSection": "Cargar archivos multimedia ",
        "broadcastSection": "Retransmitir",
        "walletSection": "Mi Cartera",
        "profitSection": "Calculadora de beneficios",
        "peers": "Peers:",
        "login": "Iniciar sesión",
        "logout": "Cerrar sesión",
        "register": "Registro",
        "search": "Buscar",
        "terms": "Terms",
        "contact": "Contact",
        "imprint": "Impreso",
        "creators": "Creators",
        "privacyPolicy": "Privacy Policy",
        "copyrightPolicy": "Copyright Policy",
        "miningSection": "Start Mining",
        "subscriptions": "Subscriptions",
        "categories": "Categorias",
        "block": "Blocks - Want",
        "airtimeID": "AirTime ID",
        "airtimeStats": "AirTime Statistics",
        "airtimeRecorded": "Recorded",
        "airtimeUnprocessed": "Unprocessed",
        "airtimeConfirmed": "Confirmed",
        "airtimeRejected": "Rejected",
        "airtimePendingEvents": "Pending Events",
        "airtimeUnsubmitted": "Unsubmitted",
        "airtimeLastPayment": "Last Payment",
        "airtimePaidBalance": "Paid Balance",
        "airtimeUnpaidBalance": "Unpaid Balance",
        "sidebarVersion": "Version"
    },
    "Terms": {
        "termsTitle": "Términos y Condiciones",
        "termsTerms": "Términos y Condiciones",
        "termsText": "Estos Términos y Condiciones se aplican al uso de cualquiera de los servicios, productos y/o páginas web de IPBC.io y Bit.Tube (en lo sucesivo \"la compañía\") y a los servicios que se detallan a continuación. Al otorgarle la posibilidad de suscribirse, usar y/o encargar, la compañía le presenta el siguiente contrato. Usted acepta estos términos al crear una cuenta como cliente, usar los servicios o al seguir usando los servicios una vez que se hubiera realizado un cambio y se le hubiera comunicado dicho cambio. Como la compañía no guarda una copia para usted, debe leer, imprimir y conservar una copia de estos términos.",
        "termsPolicy": "Política de privacidad",
        "policyText": "Su privacidad es muy importante para nosotros. Por favor lea la política de privacidad que describe qué tipo de información recopilamos de usted y sus dispositivos, y cómo usamos dicha información. La política de privacidad estipula también cómo la compañía usa sus contenidos, es decir, sus publicaciones o las opiniones que da a la compañía a través de los servicios, y archivos, fotos, documentos, audios, trabajos digitales y vídeos, así como los comentarios que sube, salva o comparte a través de dichos servicios.",
        "termsConduct": "Código de conducta",
        "conductText1": "Es necesario el comportamiento legalmente correcto por parte de los usuarios de los servicios de la compañía, el cual está sujeto a unas reglas con las cuales la compañía está comprometida.",
        "conductText2": "Los contenidos y acciones que violen estas normas no están permitidos. Al registrarse en alguno de los servicios de la compañía usted acepta cumplir estas reglas:",
        "conductRule1": "No lleve a cabo ninguna acción ilegal.",
        "conductRule2": "Las actividades que supongan un abuso, daño o amenaza a niños están prohibidas.",
        "conductRule3": "Está prohibido publicar o usar contenido inapropiado o material que viole los derechos de otros.",
        "conductRule4": "Están prohibidos los actos que le perjudiquen a usted, al servicio o a terceras personas (tales como hostigar a otros para difundir contenido de índole terrorista, incitación al odio, o llamamiento a la violencia o a la discriminación contra otros).",
        "conductRule5": "No viole ningún otro derecho, como compartir sin autorización contenido protegido por derechos de autor.",
        "conductRule6": "Están prohibidas las acciones que violen la privacidad de otros.",
        "conductText3": "Nos reservamos el derecho a bloquear el acceso a sus contenidos a través de nuestros servicios si usted viola las reglas que permiten el uso de dichos servicios.",
        "conductText4": "Así mismo nos reservamos el derecho a eliminarle del servicio si nos damos cuenta de que está incurriendo en la violación de las leyes aplicables o de estos términos.",
        "conductText5": "Como parte del control de presuntas violaciones de estos términos, la compañía se reserva el derecho a revisar los contenidos, pero nunca supervisamos en ningún momento el uso de los servicios.",
        "conductText6": "El uso de algunos de los servicios requiere disponer de una cuenta de usuario para poder ser utilizados. Por medio de esta cuenta registrada, puede iniciar sesión en el sitio web y usar dichos servicios.",
        "conductText7": "Puede registrar su cuenta de usuario online. Al hacer esto, usted declara que para la creación de esta cuenta usted no está proporcionando información falsa, inexacta o engañosa.",
        "conductText8": "Si crea una cuenta de usuario para una entidad legal (es decir, para su propia compañía o su empleador), asegúrese de que dispone de la autorización legal de esta entidad para llevar a cabo el registro en su nombre.",
        "conductText9": "Su cuenta de usuario no puede ser transferida a otro usuario u otra entidad legal. Usted es el único responsable de la seguridad de los datos de la cuenta y de la información aportada necesaria para poder iniciar sesión. Usted será responsable de todas las acciones relacionadas con su cuenta de usuario.",
        "conductText10": "Por medio del registro de su cuenta, usted declara que tiene la edad legal para hacerlo, o que usted dispone del consentimiento de sus padres o tutores legales.",
        "conductText11": "Usted puede cerrar en cualquier momento su cuenta sin tener que dar un motivo para ello. Por medio de esta acción, ya no dispondrá de los derechos para acceder a algunos servicios. Mantendremos la cuenta en suspensión durante 30 días. Durante este intervalo de tiempo, usted puede reactivarla en cualquier momento. Después de estos 30 días, solo podrá acceder a estos servicios creando una nueva cuenta.",
        "conductText12": "Cerrar su cuenta tiene varias consecuencias:",
        "conductRule7": "Usted pierde el derecho a usar estos servicios.",
        "conductRule8": "Todos los datos relacionados con su cuenta de usuario serán borrados de la base de datos de la compañía.",
        "conductRule9": "Todo el contenido que usted haya subido a través de los servicios permanecerá intacto y accesible.",
        "conductText13": "Para poder usar nuestros servicios, es necesario disponer de conexión a Internet y/o plan de datos móviles. Posiblemente necesitará adquirir equipos adicionales tales como auriculares, una cámara y/o un micrófono. Usted será responsable de adquirir y/o mantener estas conexiones a Internet, cuotas mensuales, contratos y equipos. Las cuotas y gastos necesarios para ello son su responsabilidad y son adicionales al uso de los servicios. No reembolsaremos estos gastos. Consulte a su proveedor si le cobrará y en qué cuantía. Estamos legalmente obligados a mantenerle informado acerca de las novedades importantes y sobre los cambios en los servicios. Le enviaremos notificaciones e información al correo electrónico asociado con su cuenta de usuario.",
        "conductText14": "Un servicio de soporte al cliente está disponible en IPBC.io/contact_us. Si está ubicado en Europa y su incidencia no puede ser resuelta a través de nuestros canales de soporte al cliente, tiene la opción de enviar su asunto a la Plataforma Europea de Resolución de Conflictos en Línea a webgate.ec.europa.eu/odr/main/index.cfm?event=main.home.show. El correo electrónico de la persona de contacto de IPBC.io o Bit.Tube que será presentado es odr@IPBC.io. Por favor tenga en cuenta que esta dirección de correo electrónico es solo para el uso en relación con la Plataforma Europea de Resolución de Conflictos en Línea y no se trata de un contacto para soporte general o preguntas.",
        "termsContent": "Contenido",
        "contentText1": "Por medio de nuestros servicios usted puede guardar, enviar o recibir contenidos. No recibimos la propiedad de sus contenidos. La propiedad de sus contenidos sigue siendo suya en todo momento y solo usted es responsable de ella. Through our services you can save, send or receive content.",
        "contentText2": "Cuando usted sube, publica o comparte sus contenidos por medio de nuestros servicios, usted consiente expresamente que cualquier persona que tenga acceso a ellos puede usarlos, almacenarlos, guardarlos, reproducirlos, mostrarlos y transmitirlos de forma gratuita bajo los términos de este acuerdo de derechos de autor.",
        "contentText3": "Si no desea que otros usuarios dispongan de esa opción, asegúrese de establecer por consiguiente su configuración de privacidad y mantenga ocultos los enlaces a los mismos.",
        "contentText4": "Usted garantiza que todo el contenido que haya subido o compartido en o a través de los servicios está autorizado durante el tiempo que dure este acuerdo, y que usted dispone y dispondrá de todos los derechos necesarios en relación a este contenido.",
        "contentText5": "Usted garantiza que, durante la vigencia de este acuerdo, la recopilación, el uso y la retención de todo el contenido cargado o compartido por usted en o a través de los servicios no viola ninguna ley ni los derechos de los demás.",
        "contentText6": "La compañía no se hace responsable de su contenido o de los materiales que otros suben, guardan o envían a través de sus servicios.",
        "contentText7": "En la medida de lo necesario, otorga a la empresa una licencia de propiedad intelectual mundial, libre de royalties , para usar su contenido de la siguiente manera:",
        "contentRule1": "Cambiar el tamaño, forma o formato de su contenido para facilitar una visualización y almacenamiento óptimo.",
        "contentRule2": "Para mejorar los servicios de la compañía.",
        "contentRule3": "Para compartir o mostrar el contenido.",
        "contentText8": "Desde el momento en que haya hecho su contenido público o disponible online por medio de uno de los servicios, su contenido puede aparecer en demos o materiales de promoción de los servicios de la compañía.",
        "termsDRM": "DRM y otros materiales protegidos por derechos de autor",
        "DRMText1": "Si usa material protegido por Digital Rights Management (DRM) o material protegido por derechos de autor, como cierto tipo de música, juegos y películas, los servicios de la compañía pueden conectarse automáticamente a un servidor de derechos online y denegar la entrada de ese contenido a los servicios de la compañía. Las entradas relacionadas con DRM y con la infracción de derechos de autor pueden también ser utilizadas para eliminar o para asignar estas entradas.",
        "termsService": "Disponibilidad del servicio",
        "serviceText1": "Los servicios ofrecidos por la compañía pueden no estar disponibles de vez en cuando, ser ofrecidos solo por un tiempo limitado, o pueden variar en función de la región o del dispositivo. Para todos los servicios de la compañía, nos esforzamos por mantener el servicio en funcionamiento en todo momento; sin embargo, al igual que con todos los servicios online, las interrupciones ocasionales y el tiempo de inactividad son inevitables. En caso de tiempo de inactividad o una interrupción de los servicios, es posible que temporalmente no pueda recuperar o acceder a su contenido.",
        "serviceText2": "En relación a los servicios a los que se accede via servicios o apps de terceras partes, la compañía no es responsable de los mismos y no puede influir en su disponibilidad.",
        "termsUse": "Uso de servicios y apps de terceras partes",
        "useText1": "Los servicios de la compañía proporcionan la posibilidad de acceder, localizar o comprar productos, servicios, sitios web, enlaces, contenidos, materiales, juegos o aplicaciones de terceras partes (cualquier persona natural o jurídica que no sea parte de la compañía).",
        "useText2": "Las aplicaciones y los servicios de terceros pueden permitirle guardar su contenido o datos en el editor, proveedor u operador de aplicaciones y servicios de terceros. Las aplicaciones y servicios de terceros pueden estar provistas de políticas de privacidad separadas o requerir la aceptación de términos de servicio adicionales antes de proceder a su instalación.",
        "useText3": "La compañía no es responsable de estos servicios y aplicaciones de terceros. Estos términos no se ven afectados por ningún término adicional de terceros.",
        "useText4": "Usted acepta asumir todos los riesgos y responsabilidades derivados del uso de estas aplicaciones y servicios de terceros, y la compañía no es responsable de ningún problema que surja de su uso de esas aplicaciones y servicios de terceros. La empresa no es responsable de la información proporcionada por terceros.",
        "useText5": " Cambios a este acuerdo: si la compañía tiene la intención de cambiar estos términos, recibirá la información debida en la dirección de correo electrónico asociada con su cuenta de usuario antes de que los cambios entren en vigencia. Al continuar utilizando los servicios después de que el cambio haya entrado en vigencia, usted acepta estos cambios. Si no acepta los cambios, deberá cerrar su cuenta de usuario.",
        "useText6": "Estamos autorizados a cambiar estos términos:",
        "useRule1": "En la medida en que esto sea necesario debido a la legislación internacional o nacional aplicable.",
        "useRule2": "Si es requerido por consejo y / o instrucción basada en la ley aplicable.",
        "useRule3": "Si es necesario para un desarrollo adicional de los servicios de la empresa o por razones técnicas.",
        "useRule4": "Para requisitos operacionales resultantes de los servicios de la compañía.",
        "useRule5": "Para cualquier modificación de los términos que sea beneficiosa para los usuarios de los servicios de la compañía.",
        "termsLicense": "Licencia de Software",
        "licenseText1": "A menos que sea aplicable un acuerdo específico de licencia de una compañía, el software que le proporcionamos como parte de los servicios está sujeto a estos términos.",
        "licenseText2": "Si cumple con estos términos, le otorgamos el derecho de instalar y utilizar una copia del software en cualquiera de sus dispositivos por todo el mundo para el uso de los servicios de la compañía. Cualquier software o sitio web que sea parte de los servicios puede contener código de terceros. Si se incluyen códigos de terceros, los terceros que posean el código le otorgarán la licencia, no la compañía. Todas las referencias al código de terceros, en su caso, son solo para su información.",
        "licenseText3": "Cualquier software de la compañía tiene licencia y no se vende. Todos los derechos del software que no se otorgan específicamente en este documento están reservados por la empresa.",
        "licenseText4": "No tiene derecho a hacer lo siguiente con esta licencia, excepto lo permitido por la ley aplicable:",
        "licenseRule1": "Excluir las medidas tecnológicas de protección en relación con el software y / o los servicios.",
        "licenseRule2": "Excepto en lo que respecta a los componentes de fuente abierta, no puede desensamblar, descompilar, descifrar, piratear, emular, explotar o realizar ingeniería inversa en ninguna parte del software, excepto si lo permitan específicamente las leyes de propiedad intelectual aplicables.",
        "licenseRule3": "El uso de los servicios de cualquier forma no autorizada.",
        "termsUpdates": "Actualizaciones",
        "updateText1": "El software está autorizado para ejecutar comprobaciones automáticas de las versiones de software instaladas. En la medida de lo necesario para proporcionar, ampliar o desarrollar aún más los servicios, se realiza una actualización de software o un cambio de configuración sin cargo adicional para el usuario.",
        "updateText2": "Se puede requerir al usuario que actualice el software para continuar usando los servicios.",
        "updateText3": "La empresa no está obligada a proporcionar actualizaciones sobre cambios o actualizaciones del sistema operativo, y no garantiza el soporte para la versión mejorada del sistema operativo para el que usted ha otorgado licencia al software.",
        "updateText4": "Se llevan a cabo esfuerzos constantes para mejorar, expandir o ampliar los servicios. La empresa puede cambiar sus servicios, eliminar funciones o modificar o prohibir el acceso a aplicaciones y servicios de terceros en cualquier momento. La compañía le notificará con anticipación si un cambio en los servicios puede provocar que pierda acceso a su contenido. En el caso de los servicios de pago, la compañía le notificará con anticipación acerca de los cambios importantes en los mismos. La compañía no tiene la obligación de proporcionar o intercambiar materiales previamente adquiridos, productos digitales o aplicaciones para volver a descargar, excepto en la medida en que lo permita la ley aplicable. Si la compañía canceló un servicio de pago, esta le reembolsará la cuantía que pagó por dicho servicio durante el período en que no hubiera podido usarlo.",
        "termsLiability": "Responsabilidad",
        "liabilityText1": "La empresa no es responsable del contenido, incluidos los enlaces a sitios web de terceros y actividades proporcionadas por los usuarios. Tanto el contenido como las actividades no son atribuibles a la empresa ni reflejan la opinión de la empresa.",
        "liabilityText2": "La exclusión de responsabilidad por obligaciones esenciales en virtud del contrato es responsabilidad de la empresa.",
        "liabilityText3": "Ni la empresa ni sus agentes indirectos y / o representantes legales son responsables de ningún daño indirecto, incluidas pérdidas financieras, como la pérdida de beneficios.",
        "liabilityText4": "La compañía no será responsable por el incumplimiento o demora de sus obligaciones bajo estas disposiciones si tal incumplimiento o demora se debe a circunstancias fuera del control razonable de la compañía (por ejemplo, conflictos laborales, fuerza mayor, guerra, actos terroristas, daño malicioso, accidentes o cumplimiento de la ley aplicable o una orden oficial). La compañía hace todos los esfuerzos posibles para minimizar el impacto de dichos eventos y para cumplir con sus obligaciones de forma que no se vean afectadas.",
        "termsGoverning": "Ley aplicable, jurisdicción, empresa contratante",
        "GoverningText1": "Para todos los servicios, la empresa contratante es Interplanetary Broadcast Coin SL, Calle Azucareros 34, Polígono San Jerónimo, 38312 La Orotava, Tenerife, España. Todos las reclamaciones relacionadas con servicios gratuitos se regirán por las leyes de España, sin perjuicio de las leyes obligatorias aplicables en el país en el que le ofrecemos los servicios y en los que tiene su residencia habitual. Las leyes del país en el que le ofrecemos los servicios y donde usted tiene su residencia habitual rigen todas las reclamaciones en relación con los servicios de pago."
    },
    "Policy": {
        "privacyPolicy": "Privacy Policy",
        "privacy": "BitTube respects your privacy",
        "privacyText1": "By using the company’s services you entrust us with your data. This Privacy Policy will be explain what kind of information we collect, for what purposes we collect it and what we do with the collected data.",
        "privacyText2": "Protecting your data is extremely important to us, so you should take your time to read this Privacy Policy carefully. We have done our best to make it as straightforward as possible, but if you are not familiar with terms such as “cookies” or “browser”, we recommend finding out what those words refer to first.",
        "privacyText3": "In this Privacy Policy we explain:",
        "privacyText4": "What type of data we collect and why.",
        "privacyText5": "How we use this data.",
        "privacyText6": "What options you have available to you to control and update the data collection.",
        "privacyText7": "If you have questions related to the Privacy Policy, feel free to contact us at any time.",
        "information": "The type of information we collect",
        "informationText1": "We collect information in order to provide a better service to all of our users, from basic features such as identifying the language you use, to more complex ones such as the features that you find particularly useful, the topics (categories) that are most important to you or the content that you might find interesting. We receive data from cookies, error messages and usage data of the services, among other sources.",
        "conduct": "Code of Conduct",
        "conductText1": "Information that you directly provide to us: in order to use several services, you must first create a user account. Therefore we ask you to provide some personal data such as your name, e-mail address and so on.",
        "conductText2": "Information we receive due to your use of our services: we collect information about the services you use and about the way you use them. For example, when you are accessing certain content or providing certain content:",
        "conductText3": "Device information such as hardware, operating system and browser, as far as they are useful for our services and their improvement.",
        "conductText4": "Log data such as search queries, session duration, history, language and crashes.",
        "conductText5": "Cookies created while using the services.",
        "conductText6": "Geolocation data.",
        "conductText7": "Local storage of personal user data in cookies on the used device or in the local storage areas.",
        "technologies": "Cookies and similar technologies",
        "technologiesText1": "The cookies we use do not collect personal information about our users (name, surname, address or any other personal information). The information provided by cookies is valuable as it helps us to improve the service we offer our users. We thank you for accepting them on the website and remind you that you can configure your browser to accept the cookies we send or not, or that the browser notifies you when a server wants to save a cookie.",
        "cookies": "What cookies do we use and why?",
        "cookiesTitle1": "Session cookie",
        "cookiesText1": "With this session cookie, we can see if the user has accepted the use of cookies in order to dismiss the warning. In this cookie, we store all settings that the user makes to configure the services, such as language, home page, preferences or other.",
        "cookiesText2": "The login, the automatic authentification information if desired, the security settings and the information related to social media will be stored here.",
        "cookiesTitle2": "Tab-Cookie",
        "cookiesText3": "With this cookie, we can see what tab was last accessed, so that next time you visit the page, you wil be led to the same one.",
        "cookiesTitle3": "Google Analytics",
        "cookiesText4": "These are persistent cookies and are used as part of our web analytics activities to control traffic and report on how the users use our website. Cookies are used to collect anonymous data about the user browing habits on the internet. The information collected allows us to analyze trends and make improvements to our website. The following detailed explanation lists some types of Google Analytics cookies: – UTMA – this cookie keeps track of how many times a user visited our website, when they first visited it, and the last time they visited it. – UTMB and UTMC – these cookies work together to calculate the visit duration. UTMB collects information about the exact time a visitor remains on our website, while UTMC collects information about the exact time a visitor leaves the site. UTMB expires at the end of the session. UTMC waits 30 minutes and then expires. This time frame is necessary to ensure there are no additional activities. – UTMZ – this cookie tracks where the visitor came from, for example, which search engine was used, which link was clicked, which tag is used and from which part of the world the user accesses our website. – UTMV – this is a cookie that uses which audience areas have been won by the offer.",
        "cookiesText5": "You can delete or control your cookies at any time. You can actively influence the cookie control of your browser yourself:",
        "cookiesText6": "Microsoft Internet Explorer, in the Settings menu, View Advanced Settings, Cookies.",
        "cookiesText7": "Firefox, in the Settings, Privacy and Security, History, Cookies menu.",
        "cookiesText8": "Chrome, in the Settings, Advanced, Security, and Privacy menu.",
        "cookiesText9": "Opera, in the Settings menu, Cookies.",
        "cookiesText10": "If you use another browser, you will find these steps in the user manual of the browser.",
        "cookiesText11": "Google has also developed a browser plug-in that disables sending data to the Google Analytics tool. You can download it here:",
        "collected": "How do we use the collected information?",
        "collectedText1": "We use the information collected through our services to provide, maintain, protect, and improve our services, to develop new ones and to protect our users. We may use the name you provide for your user account for all services we provide that require a user account.",
        "collectedText2": "If you have a user account, the company may display your profile name, profile picture, and the actions you perform on the company’s services associated with your user account in its services, advertisements, and other commercial contexts. This applies, for example, to streaming, following certain people or entities, or comments you post. The company pays attention to the sharing and visibility settings that you make in your user account.",
        "ServiceAvailability": "Service availability",
        "ServiceAvailabilityText0": "Personal data is collected for the following purposes and uses the following services:",
        "ServiceAvailabilityTitle1": "Analytics",
        "ServiceAvailabilityText1": "The analytics services allow to analyze the user’s behavior in order to improve the services with this information.",
        "ServiceAvailabilityTitle2": "Google Analytics (Google Inc.)",
        "ServiceAvailabilityText2": "Google Analytics is a web analytics service provided by Google Inc. (Google). Google uses the data collected to track and review the use of the company’s services to report on activities and to share them with other Google services. Google can use the data collected to contextualize and personalize the ads on its own ad network.",
        "ServiceAvailabilityTitle3": "Contact with the user",
        "ServiceAvailabilityText3": "By completing the contact form, the user authorizes this application to use these details to respond to requests for information, offers, or any other type of request, as indicated in the header of the form.",
        "share": "Information we share",
        "shareText1": "We do not share personally identifiable information with companies, organizations, or individuals outside the company except in any of the following circumstances:",
        "shareTitle1": "With your permission",
        "shareText2": "Your personal information will be shared with companies, organizations or individuals outside of the company, only if we have obtained your consent. For the transmission of any sensitive categories of personal data, we require your express consent.",
        "shareTitle2": "For the processing through third-parties",
        "shareText3": "We provide personal information to our partners, other trusted companies, or individuals who process them on our behalf. This is done on based on our instructions and in compliance with our privacy policy and other appropriate confidentiality and security measures.",
        "shareTitle3": "For legal reasons",
        "shareText4": "We will share personally identifiable information with companies, organizations, or individuals outside of the company if we have a good-faith belief that access, use, storage, or sharing this information is absolutely necessary in order to:",
        "shareText5": "comply with applicable laws, regulations or legal procedures, or to comply with an enforceable official order.",
        "shareText6": "enforce applicable terms of use, including investigating potential violations.",
        "shareText7": "detect, prevent or otherwise fight fraud, technical or security problems.",
        "shareText8": "protect the rights, property or security of the company, our users or the public from harm, to the extent permitted or required by law.",
        "shareText9": "If the company is involved in a business merge, acquisition or sale of assets, we will continue to ensure the confidentiality of any personal information and we will notify the affected users before any personal information is transmitted or becomes subject to any other privacy policy.",
        "personalInformation": "Access and update your personal information",
        "personalInformationText1": "Whenever you use our services, we strive to give you access to your personal information. Should this information be inaccurate, we will endeavor to provide you with the ability to update or remove it without delay, unless we retain it for legitimate business or legal purposes. In the event of updating your personal information, we may require proof of your identity before we implement your request.",
        "personalInformationText2": "We may reject requests that are repeated inappropriately, that require disproportionate technical effort (such as developing a new system or fundamentally changing an existing practice), that put at risk the protection of third-party personal data or that are difficult to implement without extreme difficulty (for example, requests for data stored in backup systems). Provided that we can grant access and the correction of data, this will be free of charge in principle, except in cases where this would require a disproportionate effort.",
        "personalInformationText3": "We strive to provide our services in a manner that protects the data from accidental or willful destruction. For this reason, we may not immediately delete any duplicate pieces of data that you have deleted from our services from our active servers and will not remove that data from our backup systems.",
        "dataProcessing": "Additional information for data collection and data processing",
        "dataProcessingText1": "Everyone has different concerns about privacy. Our goal is to clarify what information we collect so that you can make meaningful decisions about how to use it. You can also set your browser to block all cookies, including the cookies associated with our services, or to display a message when a cookie is set by us. However, keep in mind that many of our services may not work properly if you have disabled the cookies. For example, we will not be able to save your preferred language setting.",
        "dataSafety": "Data safety",
        "dataSafetyTitle1": "Personal information (or Data)",
        "dataSafetyText1": "We make every effort to protect our users against unauthorized access or unauthorized alteration, disclosure or destruction of data.",
        "dataSafetyText2": "Especially:",
        "dataSafetyText3": "we encrypt our connections with the use of end-to-end encyption (256 Bit AES),",
        "dataSafetyText4": "we regularly check our procedures for collection, storage and processing, including physical security measures, to protect against unauthorized access to systems,",
        "dataSafetyText5": "we restrict the access to personal information to company employees and contractors who need to access the data in order to process it for us and who are subject to strict confidentiality obligations and disciplinary action or termination if they fail to comply with these obligations.",
        "area": "Area of application of the Privacy Policy",
        "areaText1": "Our Privacy Policy may change from time to time. All changes to the Privacy Policy will be posted by us on this page. If the changes are consistent, we will provide an even clearer notification (including, in the case of certain services, an e-mail notification of changes to the Privacy Policy).",
        "contact": "Contact us",
        "contactText1": "If you have any questions related to this Privacy Policy, please do not hesitate to contact us."
    },
    "Copyright":{
        "title": "Copyright",
        "copyright": "Copyright on BitTube",
        "copyrightText1": "BitTube is a search engine that only displays links to external data. All data accessible via these links are the responsibility of the IPFS users who have uploaded it. BitTube will never be able to delete this information in the event of copyright infringement by these users since BitTube has no administrative access to the IPFS network. On behalf of the actual rights holder, BitTube can remove entries from the BitTube search engine. In this way, however, the data remains accessible via the hash value with every IPFS reader from the IPFS network if a user knows this hash value or the link is stored in another search engine.",
        "copyrightText2": "Alternatively, BitTube may assign the entries to the correct copyright holder, at least within the BitTube search engine, if this one has a BitTube user account and thus make the content liable for access via the BitTube Reader. Thus, the legitimate owner can generate income from this point in time despite the original copyright infringement with his data within the BitTube Services.",
        "copyrightText3": "BitTube never owns the content of any user. The copyright always remains with the copyright holder. For BitTube, copyright is a worldwide accepted right of the creator. BitTube supports copyright holders to generate revenue from their content worldwide directly. BitTube removes intermediate earners from this revenue chain, who retain their own disproportionately high amounts of copyright income through the control and limitation of foreign copyrights.",
        "reportCopyright": "Report copyright violation at"
    },
    "Navbar":{
        "search": "Search",
        "login": "Login",
        "register": "Register",
        "logout": "Logout",
        "homeSection": "Home",
        "trendingSection": "Trending",
        "newcomersSection": "Newcomers",
        "liveSection": "Live",
        "uploadSection": "Upload Media",
        "broadcastSection": "Broadcast",
        "walletSection": "My Wallet",
        "profitSection": "Profit Calculator",
        "userProfile": "User Profile",
        "searchResult": "Search results",
        "play": "Play",
        "terms": "Terms and Conditions",
        "startMining": "Start mining",
        "filtered": "Filtered by: ",
        "for": "for",
        "limitResults": "Limit the results",
        "limitResultsMessage" : "a maximum of 10 entries per type will be displayed",
        "browseCategories" : "Browse Categories",
        "filter": "CLEAR FILTER",
        "subscriptions": "Subscriptions"
    },
    "Version":{
        "versionMissmatchTitle" : "Version outdated",
        "versionMissmatchText" : "Your version seems to be outdated. Please clear your cache and reload the page. If this doesn't solve the problem please clear your dns cache.",
        "versionMissmatchButton" : "OK"
    },
    "Mining":{
        "download": "Download",
        "downloadPlugin": "Download TUBE miner",
        "mining": "Mining",
        "startMining": "Start mining",
        "stopMining": "Stop mining",
        "cpuCore": "CPU Cores:",
        "gpuCore": "GPU Core",
        "activateGpu": "Activate GPU",
        "hashate": "Hashrate",
        "result": "Results",
        "connection": "Connection",
        "threadID": "Thread ID",
        "totals": "Totals:",
        "highest": "Highest",
        "miningSince": "Mining since",
        "resultReport": "Result Report",
        "difficulty": "Difficulty",
        "goodResults": "Good results",
        "avgResult": "Avg result time",
        "poolSide": "Pool-side hashes",
        "top10": "Top 10 best results found",
        "errorDetails": "Error details",
        "errorText": "Error text",
        "count": "Count",
        "lastSeen": "Last Seen",
        "connectionReport": "Connection Report",
        "error": "Error",
        "poolAddress": "Pool address",
        "connectedSince": "Connected since",
        "poolPing": "Pool ping time",
        "networkError": "Network error log",
        "hashrateReport": "Hashrate Report",
        "stats": "Stats",
        "myWallet": "My Wallet:",
        "swalButtonConfirm": "Ok",
        "swalTitle": "Miner offline",
        "swalText":"We are detecting that the miner software is not running. Please start the miner.",
        "instructions": "Instructions",
        "instructions1": "If this is your first time, click the download button",
        "Instructions2": "Unpack and start bittube-miner.exe",
        "Instructions3": "Choose 'expert = no' to start mining to your My Wallet address",
        "Instructions4": "If you are an expert, visit ",
        "Instructions5": "For more information, visit ",
        "GpuDetectedNameOf": "GPu Detected - "
    },
    "PayVideo": {
        "alreadyPurchased": "Product already purchased.",
        "alreayPurchasedText": "You already purchased this product but the payment hasn't arrived now.",
        "walletNotAvailable": "Wallet not available",
        "walletNotAvailableText1": "Wallet is not available, please try it later.",
        "ok": "OK",
        "lifetimePeriod": "Purchase lifetime.",
        "rentalPeriod": "Rental",
        "rentalHours": "hours.",
        "currencyPrice": "Transaction currency",
        "price": "price:",
        "usdCurrency": "USD.",
        "tubeCurrency": "TUBE.",
        "payVideoPurchase": "Purchase",
        "payVideoCancel": "Cancel",
        "processingPurchase": "Processing purchase",
        "convertError": "Couldn't convert to Tubes. Please try again.",
        "insuficientFunds": "Insuficient funds",
        "insuficientFundsText": "The provided wallet does not contain sufficient funds",
        "confirmButtonMyWallet": "My Wallet",
        "purchaseError": "Purchase error",
        "purchaseErrorText": "There was an error processing your transaction.",
        "successTittle": "successfully"
    },
    "Consent": {
        "contentWarning": "Adult Content Warning",
        "consentText1": "You are about to enter a website that may contain content of an adult nature. These pages are designed for ADULTS only and may include pictures and materials that some viewers may find offensive. If you are under the age of 18, if such material offends you or if it is illegal to view such material in your community please do not continue. The following terms and conditions apply to this site. Entering the site via the link below will constitute your agreement to the following terms and conditions:",
        "over18": "I am 18 years of age or older",
        "consentAccept": "I accept all resposibility for my own actions; and",
        "consentTerms": "I agree that I am legally bound to these Terms and Conditions",
        "obsenePictures": "This site may contain nudity and/or obscene pictures.",
        "consentText2": "is not our intention to offend, so if you are under 18 years of age, or feel that you may be offended by this site, please don't enter",
        "consentAcceptButton": "Ok, I am old enough",
        "consentCancelButton": "No, take me to Bit.Tube"
    },
    "Notification": {
        "newComment": "Tienes un nuevo comentario",
        "newLike": "Tienes un nuevo me gusta de ",
        "newPublish": "Tu video ha sido subido",
        "newSubscriber": "Tienes un nuevo subscriptor",
        "newTip": "Has recibido",
        "errorProcessing": "Error processing:",
        "userPublish": "New video uploaded from",
        "activatedNotify": "Notifications are activated",
        "disabledNotify": "Notifications are disabled"
    },
    "DateSince":{
        "years": "años",
        "months": "meses",
        "days": "días",
        "hours": "horas",
        "minutes": "minutos",
        "seconds": "segundos",
        "prefix": "hace"
    }
}